lspinstaller/__init__.py
lspinstaller/__main__.py
lspinstaller/cli.py
lspinstaller/config.py
lspinstaller/constants.py
lspinstaller/data/__init__.py
lspinstaller/data/sources.py
lspinstaller/data/types.py
lspinstaller/resolver/__init__.py
lspinstaller/resolver/arch.py
lspinstaller/resolver/resolver.py
lspinstaller/resolver/util/__init__.py
lspinstaller/resolver/util/fetch.py
lspinstaller/resolver/util/github.py
lspinstaller-0.2.0.dist-info/licenses/LICENSE
lspinstaller-0.2.0.dist-info/METADATA
lspinstaller-0.2.0.dist-info/WHEEL
lspinstaller-0.2.0.dist-info/entry_points.txt
lspinstaller-0.2.0.dist-info/top_level.txt
lspinstaller-0.2.0.dist-info/RECORD
