Metadata-Version: 2.4
Name: lspinstaller
Version: 0.2.0
Summary: Utility script for installing (some) LSP servers
Author-email: LunarWatcher <oliviawolfie@pm.me>
License-Expression: MIT
Project-URL: Homepage, https://codeberg.org/LunarWatcher/lspinstaller
Project-URL: Documentation, https://codeberg.org/LunarWatcher/lspinstaller
Project-URL: Repository, https://codeberg.org/LunarWatcher/lspinstaller.git
Project-URL: Issues, https://codeberg.org/LunarWatcher/lspinstaller/issues
Project-URL: Changelog, https://codeberg.org/LunarWatcher/lspinstaller/src/branch/master/CHANGELOG.md
Keywords: lsp
Classifier: Development Status :: 3 - Alpha
Classifier: Environment :: Console
Classifier: Topic :: Utilities
Classifier: Intended Audience :: Developers
Classifier: Intended Audience :: End Users/Desktop
Classifier: Programming Language :: Python :: 3
Classifier: Programming Language :: Python :: 3.10
Classifier: Programming Language :: Python :: 3.11
Classifier: Programming Language :: Python :: 3.12
Classifier: Programming Language :: Python :: 3.13
Classifier: Operating System :: POSIX :: Linux
Classifier: Operating System :: Microsoft :: Windows
Requires-Python: >=3.10
License-File: LICENSE
Requires-Dist: requests
Requires-Dist: msgspec>=0.19.0
Dynamic: license-file
